piplayer/__init__.py
piplayer-0.1.1.dist-info/METADATA
piplayer-0.1.1.dist-info/WHEEL
piplayer-0.1.1.dist-info/entry_points.txt
piplayer-0.1.1.dist-info/RECORD
