Metadata-Version: 2.1
Name: piplayer
Version: 0.1.1
Summary: A command line interface to help set up a raspberry pi as a video player.
Home-page: https://github.com/antiboredom/piplayer
Author: Sam Lavigne
Author-email: splavigne@gmail.com
Requires-Python: >=3.7,<4.0
Classifier: Programming Language :: Python :: 3
Classifier: Programming Language :: Python :: 3.7
Classifier: Programming Language :: Python :: 3.8
Classifier: Programming Language :: Python :: 3.9
Classifier: Programming Language :: Python :: 3.10
Classifier: Programming Language :: Python :: 3.11
Requires-Dist: pyyaml (>=6.0,<7.0)
Project-URL: Repository, https://github.com/antiboredom/piplayer
